{"name":"速查","slug":"速查","count":1,"postlist":[{"title":"Golang：交叉编译","uid":"a2989562c244afbcf550859cf239a080","slug":"go1","date":"2021-05-06T03:38:41.000Z","updated":"2024-06-13T14:30:24.333Z","comments":false,"path":"api/articles/go1.json","keywords":null,"cover":"https://w.wallhaven.cc/full/y8/wallhaven-y85ojk.png","text":" 什么是交叉编译交叉编译是指在一个平台上生成另一个平台上的可执行程序。 比如要在Windows系统上生成可以在Linux上运行的程序时，就需要用到交叉编译。 Golang交叉编译编译参数不同的编译参数决定了最后生成的程序能在什么平台上运行，默认为当前编译平台。 GOOS 目标平台...","link":"","photos":[],"count_time":{"symbolsCount":"2k","symbolsTime":"2 mins."},"categories":[{"name":"速查","slug":"速查","count":1,"path":"api/categories/速查.json"},{"name":"项目部署","slug":"速查/项目部署","count":1,"path":"api/categories/速查/项目部署.json"}],"tags":[{"name":"golang","slug":"golang","count":5,"path":"api/tags/golang.json"},{"name":"编译","slug":"编译","count":1,"path":"api/tags/编译.json"}],"author":{"name":"年鲤","slug":"blog-author","avatar":"https://img-blog.csdnimg.cn/20210313122054101.png","link":"/","description":"喜欢折腾，随性而为<br/>sunfish69@163.com","socials":{"github":"","twitter":"","stackoverflow":"","wechat":"","qq":"","weibo":"","zhihu":"","csdn":"","juejin":"","customs":{}}}}]}